trade/TradeConductor.py
trade/__init__.py
trade/executor/TradeExecutor.py
trade/executor/__init__.py
persuader_technology_automata_trade_executor-0.1.5.dist-info/LICENSE
persuader_technology_automata_trade_executor-0.1.5.dist-info/METADATA
persuader_technology_automata_trade_executor-0.1.5.dist-info/WHEEL
persuader_technology_automata_trade_executor-0.1.5.dist-info/top_level.txt
persuader_technology_automata_trade_executor-0.1.5.dist-info/RECORD
