Metadata-Version: 2.1
Name: persuader-technology-automata-trade-executor
Version: 0.1.5
Summary: Automata Trade Executor
Author: Persuader Technology
Author-email: software@persuader.technology
License: UNLICENSE
Classifier: Programming Language :: Python :: 3
License-File: LICENSE
Requires-Dist: persuader-technology-automata-trade-repository (>=0.1.7)
